primenumbers/__init__.py
primenumbers_eipos-1.0.dist-info/LICENSE
primenumbers_eipos-1.0.dist-info/METADATA
primenumbers_eipos-1.0.dist-info/WHEEL
primenumbers_eipos-1.0.dist-info/top_level.txt
primenumbers_eipos-1.0.dist-info/RECORD
