Metadata-Version: 2.1
Name: primenumbers-eipos
Version: 1.0
Summary: Example for check, if a number is a prime number
Home-page: UNKNOWN
Author: Isaac Díaz
Author-email: isaacpda@yahoo.es
License: GNU GPLv3
Keywords: pyoperaciones mathematical operations
Platform: UNKNOWN
Classifier: Development Status :: 4 - Beta
Classifier: Intended Audience :: Developers
Classifier: Topic :: Utilities
Classifier: License :: OSI Approved :: GNU General Public License v3 (GPLv3)
Classifier: Programming Language :: Python :: 3
Classifier: Operating System :: OS Independent
